sphinxcontrib_imageembed-0.2.1-py3.6-nspkg.pth
sphinxcontrib/imageembed.py
sphinxcontrib_imageembed-0.2.1.dist-info/AUTHORS
sphinxcontrib_imageembed-0.2.1.dist-info/LICENSE
sphinxcontrib_imageembed-0.2.1.dist-info/METADATA
sphinxcontrib_imageembed-0.2.1.dist-info/WHEEL
sphinxcontrib_imageembed-0.2.1.dist-info/namespace_packages.txt
sphinxcontrib_imageembed-0.2.1.dist-info/pbr.json
sphinxcontrib_imageembed-0.2.1.dist-info/top_level.txt
sphinxcontrib_imageembed-0.2.1.dist-info/RECORD
