Metadata-Version: 2.1
Name: sphinxcontrib-imageembed
Version: 0.2.1
Summary: Embed images directly into generated html docs.
Home-page: http://www.sphinx-doc.org/
Author: Jan Gutter
Author-email: github@jangutter.com
License: BSD
Platform: UNKNOWN
Classifier: Development Status :: 4 - Beta
Classifier: Environment :: Console
Classifier: Framework :: Sphinx :: Extension
Classifier: Intended Audience :: Developers
Classifier: License :: OSI Approved :: BSD License
Classifier: Operating System :: OS Independent
Classifier: Programming Language :: Python
Classifier: Programming Language :: Python :: 2
Classifier: Programming Language :: Python :: 2.7
Classifier: Programming Language :: Python :: 3
Classifier: Programming Language :: Python :: 3.5
Classifier: Programming Language :: Python :: 3.6
Classifier: Topic :: Documentation
Classifier: Topic :: Documentation :: Sphinx
Classifier: Topic :: Utilities
Requires-Dist: pbr
